ImagingS/_Cache.py
ImagingS/_Color.py
ImagingS/_Core.py
ImagingS/_IdObject.py
ImagingS/_Point.py
ImagingS/_Rect.py
ImagingS/_Size.py
ImagingS/__init__.py
ImagingS/Cli/__init__.py
ImagingS/Cli/__main__.py
ImagingS/Cli/instruction.py
ImagingS/Gui/__init__.py
ImagingS/Gui/__main__.py
ImagingS/Gui/app.py
ImagingS/Gui/converters.py
ImagingS/Gui/icons.py
ImagingS/Gui/graphic/_Canvas.py
ImagingS/Gui/graphic/_DrawingItem.py
ImagingS/Gui/graphic/_PainterRenderContext.py
ImagingS/Gui/graphic/__init__.py
ImagingS/Gui/interactivity/_Interactivity.py
ImagingS/Gui/interactivity/_RectClip.py
ImagingS/Gui/interactivity/__init__.py
ImagingS/Gui/interactivity/geometry/_Curve.py
ImagingS/Gui/interactivity/geometry/_Ellipse.py
ImagingS/Gui/interactivity/geometry/_Geometry.py
ImagingS/Gui/interactivity/geometry/_Line.py
ImagingS/Gui/interactivity/geometry/_Polyline.py
ImagingS/Gui/interactivity/geometry/_Rectangle.py
ImagingS/Gui/interactivity/geometry/__init__.py
ImagingS/Gui/interactivity/transform/_Rotate.py
ImagingS/Gui/interactivity/transform/_Scale.py
ImagingS/Gui/interactivity/transform/_Skew.py
ImagingS/Gui/interactivity/transform/_Transform.py
ImagingS/Gui/interactivity/transform/_Translate.py
ImagingS/Gui/interactivity/transform/__init__.py
ImagingS/Gui/models/_BrushModel.py
ImagingS/Gui/models/_CommitCommand.py
ImagingS/Gui/models/_DrawingModel.py
ImagingS/Gui/models/_PropertyModel.py
ImagingS/Gui/models/_TransformModel.py
ImagingS/Gui/models/__init__.py
ImagingS/Gui/ui/__init__.py
ImagingS/Gui/ui/_ui_CodePage.py
ImagingS/Gui/ui/_ui_DocumentEditor.py
ImagingS/Gui/ui/_ui_MainWindow.py
ImagingS/Gui/ui/_ui_NewDocumentDialog.py
ImagingS/Gui/ui/_ui_VisualPage.py
ImagingS/Gui/uic/__init__.py
ImagingS/Gui/uic/__main__.py
ImagingS/Gui/widgets/_CodePage.py
ImagingS/Gui/widgets/_DocumentEditor.py
ImagingS/Gui/widgets/_MainWindow.py
ImagingS/Gui/widgets/_NewDocumentDialog.py
ImagingS/Gui/widgets/_VisualPage.py
ImagingS/Gui/widgets/__init__.py
ImagingS/brush/_Brush.py
imagings-1.0.1.dist-info/LICENSE
imagings-1.0.1.dist-info/METADATA
imagings-1.0.1.dist-info/WHEEL
imagings-1.0.1.dist-info/entry_points.txt
imagings-1.0.1.dist-info/top_level.txt
imagings-1.0.1.dist-info/RECORD
