Metadata-Version: 2.1
Name: imagings
Version: 1.0.1
Summary: A toolset for computer graphics and imaging processing.
Home-page: https://github.com/StardustDL/ImagingS
Author: StardustDL
Author-email: stardustdl@163.com
License: UNKNOWN
Project-URL: Bug Tracker, https://github.com/StardustDL/ImagingS/issues
Platform: UNKNOWN
Classifier: Programming Language :: Python :: 3
Classifier: License :: OSI Approved :: Mozilla Public License 2.0 (MPL 2.0)
Classifier: Operating System :: OS Independent
Requires-Python: >=3.7
License-File: LICENSE
Requires-Dist: numpy (==1.21.0)
Requires-Dist: Pillow (==8.3.1)
Requires-Dist: PyQt5 (==5.15.4)
Requires-Dist: qtawesome (==1.0.3)
